pygizmokit/__init__.py
pygizmokit/downloader/__init__.py
pygizmokit/downloader/multi_thread_downloader.py
pygizmokit/main.py
pygizmokit/markdown/__init__.py
pygizmokit/markdown/main.py
pygizmokit/markdown/obsidian_config_zipper.py
pygizmokit/markdown/readme_handler.py
pygizmokit/painter/__init__.py
pygizmokit/painter/main.py
pygizmokit/paths/__init__.py
pygizmokit/paths/main.py
pygizmokit/paths/paths.py
pygizmokit/paths/translater.py
pygizmokit/progress_bar.py
pygizmokit/rich_logger.py
pygizmokit/unzipper.py
pygizmokit-0.4.36.dist-info/LICENSE
pygizmokit-0.4.36.dist-info/METADATA
pygizmokit-0.4.36.dist-info/WHEEL
pygizmokit-0.4.36.dist-info/entry_points.txt
pygizmokit-0.4.36.dist-info/RECORD
