Metadata-Version: 2.1
Name: pygizmokit
Version: 0.4.36
Summary: 
Home-page: https://github.com/Atticuszz/pygizmokit
Author: Atticuszz
Author-email: 1831768457@qq.com
Requires-Python: >=3.10,<3.13
Classifier: Programming Language :: Python :: 3
Classifier: Programming Language :: Python :: 3.10
Classifier: Programming Language :: Python :: 3.11
Classifier: Programming Language :: Python :: 3.12
Requires-Dist: py7zr (>=0.20.8,<0.21.0)
Requires-Dist: rarfile (>=4.1,<5.0)
Requires-Dist: requests (>=2.31.0,<3.0.0)
Requires-Dist: rich (>=13.7.0,<14.0.0)
Requires-Dist: seaborn (>=0.13.2,<0.14.0)
Project-URL: Repository, https://github.com/Atticuszz/pygizmokit
